anime_pgen/Item.py
anime_pgen/__init__.py
anime_pgen/constants.py
anime_pgen/download.py
anime_pgen/main.py
anime_pgen/make.py
anime_pgen/utils/__init__.py
anime_pgen/utils/image.py
anime_pgen/utils/text.py
anime_pgen-1.0.1.dist-info/entry_points.txt
anime_pgen-1.0.1.dist-info/LICENSE
anime_pgen-1.0.1.dist-info/WHEEL
anime_pgen-1.0.1.dist-info/METADATA
anime_pgen-1.0.1.dist-info/RECORD
