Metadata-Version: 2.1
Name: anime-pgen
Version: 1.0.1
Summary: cli-утилита для генерации превью-изображений по данным Шикимори
Home-page: https://github.com/shikimori/preview-generator
License: GPL-3.0-only
Author: Vladimir Levin
Author-email: opaozhub@gmail.com
Requires-Python: >=3.9,<4.0
Classifier: License :: OSI Approved :: GNU General Public License v3 (GPLv3)
Classifier: Programming Language :: Python :: 3
Classifier: Programming Language :: Python :: 3.10
Classifier: Programming Language :: Python :: 3.9
Requires-Dist: Pillow (>=9.0.1,<10.0.0)
Requires-Dist: PyYAML (>=6.0,<7.0)
Requires-Dist: click (==8.1.3)
Requires-Dist: colour (>=0.1.5,<0.2.0)
Requires-Dist: joblib (>=1.1.0,<2.0.0)
Requires-Dist: numpy (>=1.22.3,<2.0.0)
Requires-Dist: ratelimiter (>=1.2.0,<2.0.0)
Requires-Dist: requests (>=2.27.1,<3.0.0)
Requires-Dist: typer[all] (>=0.4.0,<0.5.0)
Project-URL: Documentation, https://github.com/shikimori/preview-generator/blob/main/DOCS.md
Project-URL: Repository, https://github.com/shikimori/preview-generator
